autodiff/__init__.py
autodiff/backward/__init__.py
autodiff/backward/function.py
autodiff/backward/sym.py
autodiff/forward/__init__.py
autodiff/forward/function.py
autodiff/forward/sym.py
autodiff/vector/__init__.py
autodiff/vector/function.py
autodiff/vector/sym.py
AutoDiff_jnrw-0.0.2.dist-info/LICENSE
AutoDiff_jnrw-0.0.2.dist-info/METADATA
AutoDiff_jnrw-0.0.2.dist-info/WHEEL
AutoDiff_jnrw-0.0.2.dist-info/top_level.txt
AutoDiff_jnrw-0.0.2.dist-info/RECORD
